legos/base/__init__.py
legos/base/baseobject.py
legos/base/baseuser.py
legos/base/mixins/__init__.py
legos/base/mixins/commentable.py
legos/base/mixins/describable.py
legos/base/mixins/diskcacheable.py
legos/base/mixins/jsonable.py
legos/base/mixins/registeredtype.py
legos/base/mixins/status.py
legos/base/mixins/timestampable.py
legos/base/mixins/versionable.py
legos_base-0.0.1.dist-info/METADATA
legos_base-0.0.1.dist-info/WHEEL
legos_base-0.0.1.dist-info/top_level.txt
legos_base-0.0.1.dist-info/RECORD
