Metadata-Version: 2.1
Name: legos-base
Version: 0.0.1
Summary: A package providing generic base classes and mixins used in the legos api.
Home-page: UNKNOWN
Author: Bhavesh Pandey
Author-email: bxpandey@pm.me
License: MIT
Platform: UNKNOWN
Requires-Python: >=3.8
Provides-Extra: dev
Requires-Dist: pytest ; extra == 'dev'
Requires-Dist: pytest-bdd ; extra == 'dev'
Requires-Dist: pytest-cov ; extra == 'dev'
